LICENSE
README.md
setup.py
newyorktimes_scraper.egg-info/PKG-INFO
newyorktimes_scraper.egg-info/SOURCES.txt
newyorktimes_scraper.egg-info/dependency_links.txt
newyorktimes_scraper.egg-info/requires.txt
newyorktimes_scraper.egg-info/top_level.txt
pypi_scraper/__init__.py